[{"id": 1, "fname": "Justine", "lname": "Henin", "gender": "F", "init_lvl": 5.0, "game_pref": "Doubles", "join_date": "2022-04-08", "pref_court_id": 25, "email": "Justine.Henin@outlook.com", "password": "Password12345", "photo": "https://res.cloudinary.com/tennismatchup/image/upload/c_fill,h_200,w_200/v1/playerphotos/1"}, {"id": 2, "fname": "Roger", "lname": "Federer", "gender": "M", "init_lvl": 4.5, "game_pref": "Singles", "join_date": "2021-10-05", "pref_court_id": 1, "email": "Roger.Federer@yahoo.com", "password": "Password12345", "photo": "https://res.cloudinary.com/tennismatchup/image/upload/c_fill,h_200,w_200/v1/playerphotos/2"}, {"id": 3, "fname": "Bjorn", "lname": "Borg", "gender": "M", "init_lvl": 3.5, "game_pref": "Both", "join_date": "2020-06-20", "pref_court_id": 29, "email": "Bjorn.Borg@gmail.com", "password": "Password12345", "photo": "https://res.cloudinary.com/tennismatchup/image/upload/c_fill,h_200,w_200/v1/playerphotos/3"}, {"id": 4, "fname": "Billie", "lname": "Jean-King", "gender": "F", "init_lvl": 3.0, "game_pref": "Singles", "join_date": "2022-04-14", "pref_court_id": 11, "email": "Billie.Jean-King@gmail.com", "password": "Password12345", "photo": "https://res.cloudinary.com/tennismatchup/image/upload/c_fill,h_200,w_200/v1/playerphotos/4"}, {"id": 5, "fname": "Jimmy", "lname": "Connors", "gender": "M", "init_lvl": 2.5, "game_pref": "Singles", "join_date": "2021-07-27", "pref_court_id": 14, "email": "Jimmy.Connors@gmail.com", "password": "Password12345", "photo": "https://res.cloudinary.com/tennismatchup/image/upload/c_fill,h_200,w_200/v1/playerphotos/5"}, {"id": 6, "fname": "Nick", "lname": "Kyrgios", "gender": "M", "init_lvl": 3.5, "game_pref": "Both", "join_date": "2022-06-16", "pref_court_id": 18, "email": "Nick.Kyrgios@outlook.com", "password": "Password12345", "photo": "https://res.cloudinary.com/tennismatchup/image/upload/c_fill,h_200,w_200/v1/playerphotos/6"}, {"id": 7, "fname": "Stan", "lname": "Wawrinka", "gender": "M", "init_lvl": 2.5, "game_pref": "Doubles", "join_date": "2021-12-18", "pref_court_id": 7, "email": "Stan.Wawrinka@outlook.com", "password": "Password12345", "photo": "https://res.cloudinary.com/tennismatchup/image/upload/c_fill,h_200,w_200/v1/playerphotos/7"}, {"id": 8, "fname": "Novak", "lname": "Djokovic", "gender": "M", "init_lvl": 3.5, "game_pref": "Both", "join_date": "2020-07-15", "pref_court_id": 27, "email": "Novak.Djokovic@aol.com", "password": "Password12345", "photo": "https://res.cloudinary.com/tennismatchup/image/upload/c_fill,h_200,w_200/v1/playerphotos/8"}, {"id": 9, "fname": "Anna", "lname": "Kournikova", "gender": "F", "init_lvl": 4.5, "game_pref": "Singles", "join_date": "2021-11-06", "pref_court_id": 5, "email": "Anna.Kournikova@yahoo.com", "password": "Password12345", "photo": "https://res.cloudinary.com/tennismatchup/image/upload/c_fill,h_200,w_200/v1/playerphotos/9"}, {"id": 10, "fname": "Frances", "lname": "Tiafoe", "gender": "M", "init_lvl": 5.0, "game_pref": "Doubles", "join_date": "2020-06-15", "pref_court_id": 22, "email": "Frances.Tiafoe@gmail.com", "password": "Password12345", "photo": "https://res.cloudinary.com/tennismatchup/image/upload/c_fill,h_200,w_200/v1/playerphotos/10"}, {"id": 11, "fname": "Matteo", "lname": "Berrettini", "gender": "M", "init_lvl": 4.5, "game_pref": "Singles", "join_date": "2022-02-20", "pref_court_id": 5, "email": "Matteo.Berrettini@outlook.com", "password": "Password12345", "photo": "https://res.cloudinary.com/tennismatchup/image/upload/c_fill,h_200,w_200/v1/playerphotos/11"}, {"id": 12, "fname": "Pete", "lname": "Sampras", "gender": "M", "init_lvl": 4.5, "game_pref": "Doubles", "join_date": "2020-07-23", "pref_court_id": 21, "email": "Pete.Sampras@aol.com", "password": "Password12345", "photo": "https://res.cloudinary.com/tennismatchup/image/upload/c_fill,h_200,w_200/v1/playerphotos/12"}, {"id": 13, "fname": "Martina", "lname": "Navratilova", "gender": "F", "init_lvl": 3.0, "game_pref": "Doubles", "join_date": "2021-05-08", "pref_court_id": 28, "email": "Martina.Navratilova@aol.com", "password": "Password12345", "photo": "https://res.cloudinary.com/tennismatchup/image/upload/c_fill,h_200,w_200/v1/playerphotos/13"}, {"id": 14, "fname": "Lindsay", "lname": "Davenport", "gender": "F", "init_lvl": 3.5, "game_pref": "Singles", "join_date": "2020-03-14", "pref_court_id": 12, "email": "Lindsay.Davenport@aol.com", "password": "Password12345", "photo": "https://res.cloudinary.com/tennismatchup/image/upload/c_fill,h_200,w_200/v1/playerphotos/14"}, {"id": 15, "fname": "Coco", "lname": "Gauff", "gender": "F", "init_lvl": 3.0, "game_pref": "Singles", "join_date": "2023-01-25", "pref_court_id": 12, "email": "Coco.Gauff@gmail.com", "password": "Password12345", "photo": "https://res.cloudinary.com/tennismatchup/image/upload/c_fill,h_200,w_200/v1/playerphotos/15"}, {"id": 16, "fname": "Wesley", "lname": "Koolhof", "gender": "M", "init_lvl": 4.0, "game_pref": "Singles", "join_date": "2021-09-18", "pref_court_id": 12, "email": "Wesley.Koolhof@yahoo.com", "password": "Password12345", "photo": "https://res.cloudinary.com/tennismatchup/image/upload/c_fill,h_200,w_200/v1/playerphotos/16"}, {"id": 17, "fname": "Jessica", "lname": "Pegula", "gender": "F", "init_lvl": 2.5, "game_pref": "Doubles", "join_date": "2021-04-04", "pref_court_id": 26, "email": "Jessica.Pegula@yahoo.com", "password": "Password12345", "photo": "https://res.cloudinary.com/tennismatchup/image/upload/c_fill,h_200,w_200/v1/playerphotos/17"}, {"id": 18, "fname": "Maria", "lname": "Sharapova", "gender": "F", "init_lvl": 3.5, "game_pref": "Both", "join_date": "2022-07-22", "pref_court_id": 10, "email": "Maria.Sharapova@yahoo.com", "password": "Password12345", "photo": "https://res.cloudinary.com/tennismatchup/image/upload/c_fill,h_200,w_200/v1/playerphotos/18"}, {"id": 19, "fname": "Boris", "lname": "Becker", "gender": "M", "init_lvl": 4.5, "game_pref": "Doubles", "join_date": "2021-03-11", "pref_court_id": 5, "email": "Boris.Becker@yahoo.com", "password": "Password12345", "photo": "https://res.cloudinary.com/tennismatchup/image/upload/c_fill,h_200,w_200/v1/playerphotos/19"}, {"id": 20, "fname": "Martina", "lname": "Hingis", "gender": "F", "init_lvl": 4.0, "game_pref": "Doubles", "join_date": "2020-11-11", "pref_court_id": 17, "email": "Martina.Hingis@outlook.com", "password": "Password12345", "photo": "https://res.cloudinary.com/tennismatchup/image/upload/c_fill,h_200,w_200/v1/playerphotos/20"}, {"id": 21, "fname": "Naomi", "lname": "Osaka", "gender": "F", "init_lvl": 2.5, "game_pref": "Both", "join_date": "2023-01-29", "pref_court_id": 22, "email": "Naomi.Osaka@yahoo.com", "password": "Password12345", "photo": "https://res.cloudinary.com/tennismatchup/image/upload/c_fill,h_200,w_200/v1/playerphotos/21"}, {"id": 22, "fname": "Iga", "lname": "Swiate", "gender": "F", "init_lvl": 4.0, "game_pref": "Both", "join_date": "2022-09-18", "pref_court_id": 20, "email": "Iga.Swiate@outlook.com", "password": "Password12345", "photo": "https://res.cloudinary.com/tennismatchup/image/upload/c_fill,h_200,w_200/v1/playerphotos/22"}, {"id": 23, "fname": "Arthur", "lname": "Ashe", "gender": "M", "init_lvl": 3.0, "game_pref": "Singles", "join_date": "2020-09-08", "pref_court_id": 4, "email": "Arthur.Ashe@yahoo.com", "password": "Password12345", "photo": "https://res.cloudinary.com/tennismatchup/image/upload/c_fill,h_200,w_200/v1/playerphotos/23"}, {"id": 24, "fname": "Chris", "lname": "Evert", "gender": "F", "init_lvl": 4.5, "game_pref": "Doubles", "join_date": "2022-08-09", "pref_court_id": 20, "email": "Chris.Evert@yahoo.com", "password": "Password12345", "photo": "https://res.cloudinary.com/tennismatchup/image/upload/c_fill,h_200,w_200/v1/playerphotos/24"}, {"id": 25, "fname": "Marat", "lname": "Safin", "gender": "M", "init_lvl": 5.0, "game_pref": "Singles", "join_date": "2020-04-11", "pref_court_id": 28, "email": "Marat.Safin@gmail.com", "password": "Password12345", "photo": "https://res.cloudinary.com/tennismatchup/image/upload/c_fill,h_200,w_200/v1/playerphotos/25"}, {"id": 26, "fname": "Elena", "lname": "Rybakina", "gender": "F", "init_lvl": 4.0, "game_pref": "Singles", "join_date": "2023-02-16", "pref_court_id": 18, "email": "Elena.Rybakina@yahoo.com", "password": "Password12345", "photo": "https://res.cloudinary.com/tennismatchup/image/upload/c_fill,h_200,w_200/v1/playerphotos/26"}, {"id": 27, "fname": "Andy", "lname": "Roddick", "gender": "M", "init_lvl": 3.5, "game_pref": "Doubles", "join_date": "2020-05-31", "pref_court_id": 22, "email": "Andy.Roddick@outlook.com", "password": "Password12345", "photo": "https://res.cloudinary.com/tennismatchup/image/upload/c_fill,h_200,w_200/v1/playerphotos/27"}, {"id": 28, "fname": "Casper", "lname": "Ruud", "gender": "M", "init_lvl": 2.5, "game_pref": "Doubles", "join_date": "2021-08-11", "pref_court_id": 27, "email": "Casper.Ruud@yahoo.com", "password": "Password12345", "photo": "https://res.cloudinary.com/tennismatchup/image/upload/c_fill,h_200,w_200/v1/playerphotos/28"}, {"id": 29, "fname": "Dominic", "lname": "Thiem", "gender": "M", "init_lvl": 4.5, "game_pref": "Doubles", "join_date": "2022-04-08", "pref_court_id": 4, "email": "Dominic.Thiem@aol.com", "password": "Password12345", "photo": "https://res.cloudinary.com/tennismatchup/image/upload/c_fill,h_200,w_200/v1/playerphotos/29"}, {"id": 30, "fname": "Monica", "lname": "Seles", "gender": "F", "init_lvl": 4.5, "game_pref": "Both", "join_date": "2020-07-31", "pref_court_id": 28, "email": "Monica.Seles@aol.com", "password": "Password12345", "photo": "https://res.cloudinary.com/tennismatchup/image/upload/c_fill,h_200,w_200/v1/playerphotos/30"}, {"id": 31, "fname": "Margaret", "lname": "Court", "gender": "F", "init_lvl": 4.5, "game_pref": "Both", "join_date": "2020-06-28", "pref_court_id": 28, "email": "Margaret.Court@yahoo.com", "password": "Password12345", "photo": "https://res.cloudinary.com/tennismatchup/image/upload/c_fill,h_200,w_200/v1/playerphotos/31"}, {"id": 32, "fname": "Andy", "lname": "Murray", "gender": "M", "init_lvl": 5.0, "game_pref": "Doubles", "join_date": "2022-11-04", "pref_court_id": 5, "email": "Andy.Murray@gmail.com", "password": "Password12345", "photo": "https://res.cloudinary.com/tennismatchup/image/upload/c_fill,h_200,w_200/v1/playerphotos/32"}, {"id": 33, "fname": "John", "lname": "Isner", "gender": "M", "init_lvl": 3.5, "game_pref": "Singles", "join_date": "2020-09-01", "pref_court_id": 15, "email": "John.Isner@gmail.com", "password": "Password12345", "photo": "https://res.cloudinary.com/tennismatchup/image/upload/c_fill,h_200,w_200/v1/playerphotos/33"}, {"id": 34, "fname": "Madison", "lname": "Keys", "gender": "F", "init_lvl": 4.0, "game_pref": "Both", "join_date": "2020-07-06", "pref_court_id": 12, "email": "Madison.Keys@outlook.com", "password": "Password12345", "photo": "https://res.cloudinary.com/tennismatchup/image/upload/c_fill,h_200,w_200/v1/playerphotos/34"}, {"id": 35, "fname": "Andre", "lname": "Agassi", "gender": "M", "init_lvl": 4.5, "game_pref": "Doubles", "join_date": "2022-01-09", "pref_court_id": 2, "email": "Andre.Agassi@yahoo.com", "password": "Password12345", "photo": "https://res.cloudinary.com/tennismatchup/image/upload/c_fill,h_200,w_200/v1/playerphotos/35"}, {"id": 36, "fname": "Kim", "lname": "Clijsters", "gender": "F", "init_lvl": 2.5, "game_pref": "Singles", "join_date": "2023-02-06", "pref_court_id": 7, "email": "Kim.Clijsters@gmail.com", "password": "Password12345", "photo": "https://res.cloudinary.com/tennismatchup/image/upload/c_fill,h_200,w_200/v1/playerphotos/36"}, {"id": 37, "fname": "Rafael", "lname": "Nadal", "gender": "M", "init_lvl": 3.5, "game_pref": "Doubles", "join_date": "2020-07-23", "pref_court_id": 24, "email": "Rafael.Nadal@aol.com", "password": "Password12345", "photo": "https://res.cloudinary.com/tennismatchup/image/upload/c_fill,h_200,w_200/v1/playerphotos/37"}, {"id": 38, "fname": "Steffi", "lname": "Graf", "gender": "F", "init_lvl": 4.0, "game_pref": "Singles", "join_date": "2023-01-10", "pref_court_id": 30, "email": "Steffi.Graf@outlook.com", "password": "Password12345", "photo": "https://res.cloudinary.com/tennismatchup/image/upload/c_fill,h_200,w_200/v1/playerphotos/38"}, {"id": 39, "fname": "Venus", "lname": "Williams", "gender": "F", "init_lvl": 4.0, "game_pref": "Singles", "join_date": "2021-02-20", "pref_court_id": 14, "email": "Venus.Williams@gmail.com", "password": "Password12345", "photo": "https://res.cloudinary.com/tennismatchup/image/upload/c_fill,h_200,w_200/v1/playerphotos/39"}, {"id": 40, "fname": "Serena", "lname": "Williams", "gender": "F", "init_lvl": 2.5, "game_pref": "Singles", "join_date": "2020-03-21", "pref_court_id": 5, "email": "Serena.Williams@outlook.com", "password": "Password12345", "photo": "https://res.cloudinary.com/tennismatchup/image/upload/c_fill,h_200,w_200/v1/playerphotos/40"}, {"id": 41, "fname": "Stefanos", "lname": "Tsitsipas", "gender": "M", "init_lvl": 4.5, "game_pref": "Singles", "join_date": "2022-11-18", "pref_court_id": 4, "email": "Stefanos.Tsitsipas@outlook.com", "password": "Password12345", "photo": "https://res.cloudinary.com/tennismatchup/image/upload/c_fill,h_200,w_200/v1/playerphotos/41"}]
